setup.cfg
setup.py
Products/__init__.py
Products.ECAssignmentBox.egg-info/PKG-INFO
Products.ECAssignmentBox.egg-info/SOURCES.txt
Products.ECAssignmentBox.egg-info/dependency_links.txt
Products.ECAssignmentBox.egg-info/entry_points.txt
Products.ECAssignmentBox.egg-info/namespace_packages.txt
Products.ECAssignmentBox.egg-info/not-zip-safe
Products.ECAssignmentBox.egg-info/requires.txt
Products.ECAssignmentBox.egg-info/top_level.txt
Products.ECAssignmentBox.egg-info/browser/__init__.py
Products.ECAssignmentBox.egg-info/browser/configure.zcml
Products.ECAssignmentBox.egg-info/browser/ecab.kss
Products.ECAssignmentBox.egg-info/browser/ecab_kss.py
Products.ECAssignmentBox.egg-info/browser/ecabbase.py
Products.ECAssignmentBox.egg-info/browser/state.py
Products.ECAssignmentBox.egg-info/browser/viewlets/__init__.py
Products.ECAssignmentBox.egg-info/browser/viewlets/templates/workflow_change.pt
Products/ECAssignmentBox/CHANGES.txt
Products/ECAssignmentBox/LICENSE.GPL
Products/ECAssignmentBox/LICENSE.TXT
Products/ECAssignmentBox/README.txt
Products/ECAssignmentBox/TODO.txt
Products/ECAssignmentBox/__init__.py
Products/ECAssignmentBox/config.py
Products/ECAssignmentBox/configure.zcml
Products/ECAssignmentBox/ec_tool.png
Products/ECAssignmentBox/permissions.zcml
Products/ECAssignmentBox/profiles.zcml
Products/ECAssignmentBox/refresh.txt
Products/ECAssignmentBox/setuphandlers.py
Products/ECAssignmentBox/sharing.py
Products/ECAssignmentBox/version.txt
Products/ECAssignmentBox/Extensions/__init__.py
Products/ECAssignmentBox/Extensions/workflow_scripts.py
Products/ECAssignmentBox/PlagDetector/PlagChecker.py
Products/ECAssignmentBox/PlagDetector/PlagResult.py
Products/ECAssignmentBox/PlagDetector/PlagVisualizer.py
Products/ECAssignmentBox/PlagDetector/__init__.py
Products/ECAssignmentBox/PlagDetector/errors.py
Products/ECAssignmentBox/PlagDetector/Detection/__init__.py
Products/ECAssignmentBox/PlagDetector/Detection/algGST.py
Products/ECAssignmentBox/PlagDetector/Detection/algGSTNormal.py
Products/ECAssignmentBox/PlagDetector/Detection/algGSTPrechelt.py
Products/ECAssignmentBox/PlagDetector/Detection/algNGRAM.py
Products/ECAssignmentBox/PlagDetector/Helper/GraphicsHelper.py
Products/ECAssignmentBox/PlagDetector/Helper/PlagResultListHelper.py
Products/ECAssignmentBox/PlagDetector/Helper/XMLHelper.py
Products/ECAssignmentBox/PlagDetector/Helper/__init__.py
Products/ECAssignmentBox/PlagDetector/Normalize/__init__.py
Products/ECAssignmentBox/PlagDetector/Normalize/normNormal.py
Products/ECAssignmentBox/PlagDetector/Normalize/normPython.py
Products/ECAssignmentBox/PlagDetector/Visualize/__init__.py
Products/ECAssignmentBox/PlagDetector/Visualize/dotplot.py
Products/ECAssignmentBox/PlagDetector/Visualize/heatmap.py
Products/ECAssignmentBox/PlagDetector/Visualize/htmlMaker.py
