Metadata-Version: 1.0
Name: Products.ECAssignmentBox
Version: 1.5.1
Summary: Creation, submission and grading of online assignments (exercises, homework).
Home-page: http://plone.org/products/ecassignmentbox/
Author: Mario Amelung and Michael Piotrowski
Author-email: mario.amelung@gmx.de and mxp@dynalabs.de
License: GPL
Platform: UNKNOWN
Classifier: Framework :: Plone
Classifier: Framework :: Zope2
Classifier: Programming Language :: Python
Classifier: Topic :: Software Development :: Libraries :: Python Modules
